geo_trace-0.0.1.dist-info/METADATA
geo_trace-0.0.1.dist-info/WHEEL
geo_trace-0.0.1.dist-info/licenses/AUTHORS
geo_trace-0.0.1.dist-info/licenses/LICENSE.txt
geo_trace.libs/libgcc_s-1e52349c.so.1
geo_trace/__init__.py
geo_trace/__init__.pyi
geo_trace/geo_trace.cpython-38-x86_64-linux-gnu.so
geo_trace/py.typed
geo_trace-0.0.1.dist-info/RECORD
