Metadata-Version: 2.4
Name: geo-trace
Version: 0.0.1
Classifier: Programming Language :: Rust
Classifier: Programming Language :: Python :: Implementation :: CPython
Classifier: Programming Language :: Python :: Implementation :: PyPy
License-File: LICENSE.txt
License-File: AUTHORS
Author: Tal Amuyal <TalAmuyal@gmail.com>
Author-email: Tal Amuyal <TalAmuyal@gmail.com>
Requires-Python: >=3.8, <3.13
